.gitignore
GameOfLife_DiscreteGrid.py
LICENSE
MANIFEST.in
setup.py
setup_cython.py
uploadTopip.sh
demos/GetHelp.py
takagiabm/__init__.py
takagiabm/activation.py
takagiabm/control.py
takagiabm/datacounter.py
takagiabm/help.py
takagiabm/plottest.py
takagiabm/remoteplot2.py
takagiabm/variable.py
takagiabm/agents/__init__.py
takagiabm/agents/agent.pyx
takagiabm/agents/baseagent.py
takagiabm/agents/gridagents/__init__.py
takagiabm/agents/gridagents/discretegrid/__init__.py
takagiabm/agents/gridagents/discretegrid/discretegridagent.py
takagiabm/agents/gridagents/discretegrid/discretegridcell.py
takagiabm/agents/gridagents/freegrid/__init__.py
takagiabm/agents/gridagents/freegrid/freegridagent.py
takagiabm/agents/gridagents/freegrid/freegridcell.py
takagiabm/agents/vehicle_station/__init__.py
takagiabm/agents/vehicle_station/stations.py
takagiabm/agents/vehicle_station/vehicles.py
takagiabm/containers/__init__.py
takagiabm/containers/grid.pyx
takagiabm/containers/route.py
takagiabm/containers/grids/__init__.py
takagiabm/containers/grids/basegrid.py
takagiabm/containers/grids/discretegrid.py
takagiabm/containers/grids/freegrid.py
takagiabm/models/__init__.py
takagiabm/models/discretegridmodel.py
takagiabm/models/model.py
takagiabm/models/model.pyx
takagiabm/models/vehicle_station/__init__.py
takagiabm/models/vehicle_station/vehicleline.py
takagiabm/refresh/__init__.py
takagiabm/toolbox/__init__.py
takagiabm/toolbox/kinematics.py
takagiabm/toolbox/kinematics.pyx
takagiabm/toolbox/looks.py
takagiabm/toolbox/multiprocessor.py
takagiabm/toolbox/numbaUtils.py
takagiabm/toolbox/randomevents.py
takagiabm/toolbox/readme.md
takagiabm/toolbox/taktimecounter.py
takagiabm/toolbox/taktimecounter.pyx
takagiabm/toolbox/typeutils.py
takagiabm/toolbox/typeutils.pyx
takagiabm/visualize/__init__.py
takagiabm/visualize/hat.png
takagiabm/visualize/mainwindow.py
takagiabm/visualize/pg2.py
takagiabm/visualize/readme.md
takagiabm/visualize/takagiwidgets/__init__.py
